draft_server/__init__.py
draft_server/draft.py
twr_draft-0.2.0.dist-info/METADATA
twr_draft-0.2.0.dist-info/WHEEL
twr_draft-0.2.0.dist-info/entry_points.txt
twr_draft-0.2.0.dist-info/RECORD
