Metadata-Version: 2.4
Name: twr-draft
Version: 0.2.0
Summary: 一个功能完整的草稿管理MCP服务器，支持创建、读取、更新、删除和搜索草稿。专为单次对话设计，使用内存存储。
Project-URL: Homepage, https://github.com/yourusername/draft-mcp
Project-URL: Repository, https://github.com/yourusername/draft-mcp
Project-URL: Issues, https://github.com/yourusername/draft-mcp/issues
Author-email: TTTTWR <2116528714@qq.com>
Keywords: draft,mcp,notes,text-editor
Classifier: Development Status :: 4 - Beta
Classifier: Intended Audience :: Developers
Classifier: License :: OSI Approved :: MIT License
Classifier: Programming Language :: Python :: 3
Classifier: Programming Language :: Python :: 3.12
Requires-Python: >=3.12
Requires-Dist: fastmcp>=2.10.6
